LICENSE
README.md
setup.py
src/scrapy_toolset/__init__.py
src/scrapy_toolset/connection.py
src/scrapy_toolset/defaults.py
src/scrapy_toolset/items.py
src/scrapy_toolset/tools.py
src/scrapy_toolset.egg-info/PKG-INFO
src/scrapy_toolset.egg-info/SOURCES.txt
src/scrapy_toolset.egg-info/dependency_links.txt
src/scrapy_toolset.egg-info/requires.txt
src/scrapy_toolset.egg-info/top_level.txt
src/scrapy_toolset/dupefilters/__init__.py
src/scrapy_toolset/dupefilters/redis/__init__.py
src/scrapy_toolset/dupefilters/redis/defaults.py
src/scrapy_toolset/pipelines/__init__.py
src/scrapy_toolset/pipelines/elasticsearch.py
src/scrapy_toolset/pipelines/mongodb.py
src/scrapy_toolset/pipelines/mysql.py
src/scrapy_toolset/pipelines/rabbitmq.py
src/scrapy_toolset/scrapy_rabbitmq_scheduler/__init__.py
src/scrapy_toolset/scrapy_rabbitmq_scheduler/connection.py
src/scrapy_toolset/scrapy_rabbitmq_scheduler/defaults.py
src/scrapy_toolset/scrapy_rabbitmq_scheduler/picklecompat.py
src/scrapy_toolset/scrapy_rabbitmq_scheduler/queue.py
src/scrapy_toolset/scrapy_rabbitmq_scheduler/scheduler.py
src/scrapy_toolset/scrapy_rabbitmq_scheduler/spiders.py
src/scrapy_toolset/scrapy_rabbitmq_scheduler/utils.py
src/scrapy_toolset/scrapy_rabbitmq_scheduler/downloadermiddlewares/__init__.py
src/scrapy_toolset/scrapy_rabbitmq_scheduler/downloadermiddlewares/retry.py
src/scrapy_toolset/scrapy_rabbitmq_scheduler/spidermiddlewares/__init__.py
src/scrapy_toolset/scrapy_rabbitmq_scheduler/spidermiddlewares/autoack.py